{
	"pages": [{
			"path": "pages/index/index",
			"style": {
				"navigationStyle": "custom"
			}
		},
		{
			"path": "pages/logo/logo"
		},
		{
			"path": "pages/information/information",
			"style": {
				"navigationStyle": "custom"
			}
		},
		{
			"path": "pages/diggings/diggings"
		},
		{
			"path": "pages/participation/part",
			"style": {
				"navigationStyle": "custom"
			}
		},
		{
			"path": "pages/usInfo/user",
			"style": {
				"navigationStyle": "custom"
			}
		},
		{
			"path": "pages/Detailspage/index",
			"style": {
				"navigationBarBackgroundColor": "#171A2C", 
				"navigationBarTextStyle": "white",
				"navigationBarTitleText":"商品详情",
				"app-plus": {
					"titleNView": {
						"buttons": [
							{
								"color": "#f1f2f3",
								"float": "left", 
								"fontSize": "20px"
							}
						]
					}
				}
			}
		},
		{
			"path": "pages/announcement/index",
			"style": {
				"navigationBarBackgroundColor": "#171A2C", 
				"navigationBarTextStyle": "white",
				"navigationBarTitleText":"公告详情",
				"app-plus": {
					"titleNView": {
						"buttons": [
							{
								"color": "#f1f2f3",
								"float": "left", 
								"fontSize": "20px"
							}
						]
					}
				}
			}
		}
	],
	"tabBar": {
		"color": "#7A7E83",
		"selectedColor": "#3cc51f",
		"borderStyle": "black",
		"backgroundColor": "#ffffff",
		"list": [{
				"pagePath": "pages/index/index",
				"iconPath": "static/tabBar-icon/index.png",
				"selectedIconPath": "static/tabBar-icon/index-h.png",
				"text": "首页"
			},
			{
				"pagePath": "pages/information/information",
				"iconPath": "static/tabBar-icon/zixun.png",
				"selectedIconPath": "static/tabBar-icon/zixun-h.png",
				"text": "资讯"
			},
			{
				"pagePath": "pages/participation/part",
				"iconPath": "static/tabBar-icon/kuanquan.png",
				"selectedIconPath": "static/tabBar-icon/kuanquan-h.png",
				"text": "矿圈"
			},
			{
				"pagePath": "pages/usInfo/user",
				"iconPath": "static/tabBar-icon/myImg.png",
				"selectedIconPath": "static/tabBar-icon/myImg-h.png",
				"text": "我的"
			}
		],
		"midButton": {
			"width": "80px",
			"height": "80px",
			"text": "算力",
			"iconPath": "static/tabBar-icon/suanli.png"
		}
	},
	"globalStyle": {
		"navigationBarTextStyle": "black",
		"navigationBarBackgroundColor": "#F8F8F8",
		"backgroundColor": "#F8F8F8"
	}
}